{"title":"연합뉴스 ─ 네이버TV","url":"https://tv.naver.com/yonhapnews/clips","favicon":"https://tv.naver.com/yonhapnews/favicon.ico","elements":[{"title":"구속 면한 유아인 \"법원 판단에 감사\"…날아온 페트병에 맞기도","contents":"2:09","link":"https://tv.naver.com/v/36293870","retrieved":1684982162309,"image":"https://phinf.pstatic.net/tvcast/20230525_279/efTTd_1684980540744wR4Ny_JPEG/1684980420246.jpg?type=f194_109_blend"},{"title":"'로큰롤 여왕' 티나 터너 스위스 자택서 사망…향년 83세","contents":"2:47","link":"https://tv.naver.com/v/36293750","retrieved":1684982162311,"image":"https://phinf.pstatic.net/tvcast/20230525_262/znl05_1684980371173kbaJw_JPEG/1684979828267.jpg?type=f194_109_blend"},{"title":"[삶] 서기원 \"외국으로의 입양이 축복이라고요?...하루하루 지옥이죠\"","contents":"10:45","link":"https://tv.naver.com/v/36291573","retrieved":1684977792471,"image":"https://phinf.pstatic.net/tvcast/20230525_140/mrne0_1684976314571g5lTb_JPEG/1684972042800.jpg?type=f194_109_blend"},{"title":"[포켓이슈] 할아버지 택시기사 \"내가 이 나이에 달리는 이유는...\"","contents":"3:31","link":"https://tv.naver.com/v/36264663","retrieved":1684970300275,"image":"https://phinf.pstatic.net/tvcast/20230524_252/RjWgi_1684912200160R623I_JPEG/1684912152837.jpg?type=f194_109_blend"},{"title":"신축아파트 외벽에 '돈 주세요'…로프 타고 고공 시위한 사연","contents":"0:36","link":"https://tv.naver.com/v/36268117","retrieved":1684916560414,"image":"https://phinf.pstatic.net/tvcast/20230524_281/zE9Bx_1684916330216oos4F_JPEG/1684916225360.jpg?type=f194_109_blend"},{"title":"1인분 830만원?…기네스 신기록 아이스크림엔 뭐가?","contents":"1:38","link":"https://tv.naver.com/v/36267474","retrieved":1684916560416,"image":"https://phinf.pstatic.net/tvcast/20230524_104/9vnfx_1684915447230xSTSX_JPEG/1684915162149.jpg?type=f194_109_blend"},{"title":"러시아 패하면 다음 타깃?…러와 더 끈끈해진 중국","contents":"2:39","link":"https://tv.naver.com/v/36267216","retrieved":1684916560418,"image":"https://phinf.pstatic.net/tvcast/20230524_108/PXTp8_1684915160993EWCR8_JPEG/1684915144585.jpg?type=f194_109_blend"},{"title":"\"핵종말 가능성\"…F-16 지원 움직임에 '푸틴 오른팔' 또 핵위협","contents":"2:33","link":"https://tv.naver.com/v/36266952","retrieved":1684916560419,"image":"https://phinf.pstatic.net/tvcast/20230524_232/OyQNE_1684914838788QeQ6Q_JPEG/1684913968793.jpg?type=f194_109_blend"},{"title":"청나라 '마지막 황제' 명품시계, 예상가 갑절인 82억원에 낙찰","contents":"1:47","link":"https://tv.naver.com/v/36266933","retrieved":1684916560427,"image":"https://phinf.pstatic.net/tvcast/20230524_265/m3QQ6_16849148234327aUdT_JPEG/1684913927292.jpg?type=f194_109_blend"},{"title":"관세청 마약탐지 훈련견 14마리 분양…\"래브라도레트리버 종\"","contents":"0:57","link":"https://tv.naver.com/v/36265805","retrieved":1684916560427,"image":"https://phinf.pstatic.net/tvcast/20230524_160/RoQOj_168491353479034qhS_JPEG/1684913467320.jpg?type=f194_109_blend"},{"title":"북한 '핵위협' 때문에 바꾼다…미군 전투 조종사 새 헬멧 보니","contents":"2:44","link":"https://tv.naver.com/v/36259086","retrieved":1684905431413,"image":"https://phinf.pstatic.net/tvcast/20230524_7/U9yhM_1684905156677NhRtg_JPEG/1684905138197.jpg?type=f194_109_blend"},{"title":"발트해 상공 또 신경전…러 전투기, 미 전략폭격기와 한때 대치","contents":"2:00","link":"https://tv.naver.com/v/36258036","retrieved":1684905431414,"image":"https://phinf.pstatic.net/tvcast/20230524_140/7sgoX_1684903642221pz1TN_JPEG/1684903600959.jpg?type=f194_109_blend"},{"title":"대구 지하주차장서 전기차 충전 중 화재…150분 만에 꺼져","contents":"0:43","link":"https://tv.naver.com/v/36253926","retrieved":1684898407952,"image":"https://phinf.pstatic.net/tvcast/20230524_290/5HjXN_1684896483049icUkN_JPEG/1684896351991.jpg?type=f194_109_blend"},{"title":"첫 이틀 넘긴 러 본토 교전…\"러 갈수록 심각한 다중 위협 직면\"","contents":"2:17","link":"https://tv.naver.com/v/36253847","retrieved":1684898407952,"image":"https://phinf.pstatic.net/tvcast/20230524_153/yXtjk_16848963223983FrQR_JPEG/1684896307215.jpg?type=f194_109_blend"},{"title":"한국 시찰단 반기는 일본…후쿠시마 수산물 수입 요청도","contents":"3:04","link":"https://tv.naver.com/v/36253190","retrieved":1684895910237,"image":"https://phinf.pstatic.net/tvcast/20230524_189/MLhHc_1684895313284yXOQS_JPEG/1684895298356.jpg?type=f194_109_blend"},{"title":"8대가 한 몸처럼…블랙이글스, 말레이시아 에어쇼서 화려한 기동","contents":"1:42","link":"https://tv.naver.com/v/36230030","retrieved":1684833590219,"image":"https://phinf.pstatic.net/tvcast/20230523_144/YuYEQ_1684832664089F8sm8_JPEG/1684832311396.jpg?type=f194_109_blend"},{"title":"넘쳐나는 '우크라전 게임 체인저'? 전문가 의견 들으니…","contents":"7:07","link":"https://tv.naver.com/v/36229729","retrieved":1684833590220,"image":"https://phinf.pstatic.net/tvcast/20230524_62/3P4Y7_1684887740599Hmoe8_JPEG/1684887735097.jpg?type=f194_109_blend"},{"title":"바흐무트는 2차대전 베를린?…선전전에 열 올리는 러 언론","contents":"2:56","link":"https://tv.naver.com/v/36229362","retrieved":1684833590222,"image":"https://phinf.pstatic.net/tvcast/20230523_111/KUV2g_1684831649063yIjnO_JPEG/1684831629841.jpg?type=f194_109_blend"},{"title":"몸 비비고, 뒤에서 껴안고 …부천시의원 성추행 의혹 CCTV 보니","contents":"2:04","link":"https://tv.naver.com/v/36228975","retrieved":1684833590228,"image":"https://phinf.pstatic.net/tvcast/20230523_78/IQZtD_168483117553864nU7_JPEG/1684831162553.jpg?type=f194_109_blend"},{"title":"바흐무트 못 내준다는 우크라…\"측면서 전술적 포위\"","contents":"3:05","link":"https://tv.naver.com/v/36228153","retrieved":1684830213797,"image":"https://phinf.pstatic.net/tvcast/20230523_62/McLL3_1684830044081Y44he_JPEG/1684829876720.jpg?type=f194_109_blend"},{"title":"누리호 첫 실전발사 준비 착착…'18분58초' 비행 성공하려면?","contents":"2:35","link":"https://tv.naver.com/v/36228094","retrieved":1684830213798,"image":"https://phinf.pstatic.net/tvcast/20230523_183/f2pDQ_1684829959057gIzYu_JPEG/1684828000389.jpg?type=f194_109_blend"},{"title":"필리핀 중앙우체국 7시간 '활활'…편지·소포가 불쏘시개 됐나","contents":"1:40","link":"https://tv.naver.com/v/36223788","retrieved":1684826215523,"image":"https://phinf.pstatic.net/tvcast/20230523_40/GmmKX_16848256143146QrOu_JPEG/1684825604022.jpg?type=f194_109_blend"},{"title":"도살장 실려가던 돼지 도로에 뚝…20여분 만에 다시 붙잡혀","contents":"1:10","link":"https://tv.naver.com/v/36220953","retrieved":1684823026386,"image":"https://phinf.pstatic.net/tvcast/20230523_232/cBp1u_1684822409140MlBeg_JPEG/1684822067249.jpg?type=f194_109_blend"},{"title":"'독수리 충돌·동체착륙' F-35A 수리 견적 1천억원…폐기 검토","contents":"2:42","link":"https://tv.naver.com/v/36218183","retrieved":1684819115060,"image":"https://phinf.pstatic.net/tvcast/20230523_144/Hf0QN_1684818754981jMaAv_JPEG/1684818430215.jpg?type=f194_109_blend"},{"title":"우크라 접경 러 본토서 교전…\"상황 매우 긴박\"","contents":"2:41","link":"https://tv.naver.com/v/36217393","retrieved":1684819115061,"image":"https://phinf.pstatic.net/tvcast/20230523_125/3Wg5O_168481759160841bjg_JPEG/1684817540392.jpg?type=f194_109_blend"},{"title":"'K 정원'에 반한 영국 찰스 3세, 한국 작가 꼭 안아줬다","contents":"2:54","link":"https://tv.naver.com/v/36213495","retrieved":1684811920309,"image":"https://phinf.pstatic.net/tvcast/20230523_215/eSg9Y_16848106335967Nhvw_JPEG/1684810613264.jpg?type=f194_109_blend"},{"title":"올렸다가 지운 이유는…미 공군 SNS서 사라진 사진","contents":"2:16","link":"https://tv.naver.com/v/36212782","retrieved":1684811920311,"image":"https://phinf.pstatic.net/tvcast/20230523_179/o5XlB_1684809725527KhwnD_JPEG/1684809587649.jpg?type=f194_109_blend"},{"title":"\"이란, 지하 80ｍ에 새 핵시설…벙커버스터 한 발로는 못 뚫어\"","contents":"1:34","link":"https://tv.naver.com/v/36212375","retrieved":1684809397275,"image":"https://phinf.pstatic.net/tvcast/20230523_125/PdVSO_1684809222453Ri2os_JPEG/1684808649796.jpg?type=f194_109_blend"},{"title":"스페인 F-18 전투기 추락 순간 포착…조종사 비상 탈출 '아찔'","contents":"1:04","link":"https://tv.naver.com/v/36191269","retrieved":1684754142356,"image":"https://phinf.pstatic.net/tvcast/20230522_1/xUb23_1684752633558kLFch_JPEG/1684752613289.jpg?type=f194_109_blend"},{"title":"영국 무기 수출액 2배로 늘었다…카타르·사우디가 큰손","contents":"1:57","link":"https://tv.naver.com/v/36186240","retrieved":1684747111466,"image":"https://phinf.pstatic.net/tvcast/20230522_236/eN12x_1684745010723k50yx_JPEG/1684744999680.jpg?type=f194_109_blend"}]}