{"title":"연합뉴스 ─ 네이버TV","url":"https://tv.naver.com/yonhapnews/clips","favicon":"https://tv.naver.com/yonhapnews/favicon.ico","elements":[{"title":"북, 탄도미사일 1발 발사…부산 온 미 핵잠수함 타깃 삼은 듯","contents":"2:35","link":"https://tv.naver.com/v/44483009","retrieved":1702866666472,"image":"https://phinf.pstatic.net/tvcast/20231218_66/sry43_1702865588070uDWAh_JPEG/1702865585562.jpg?type=f194_109_blend"},{"title":"인천 호텔 주차장 화재로 54명 중경상…\"합동 감식 예정\"","contents":"1:24","link":"https://tv.naver.com/v/44480980","retrieved":1702862157507,"image":"https://phinf.pstatic.net/tvcast/20231218_137/YEZ44_17028620857153Vg80_JPEG/1702860620904.jpg?type=f194_109_blend"},{"title":"미 의회 상원 청문회실 '남성 동성애 영상' 파문","contents":"1:29","link":"https://tv.naver.com/v/44455658","retrieved":1702801264617,"image":"https://phinf.pstatic.net/tvcast/20231217_100/EEbNo_17027985431741Ocun_JPEG/1702798238738.jpg?type=f194_109_blend"},{"title":"인질 오인사살 후폭풍…가자 인큐베이터에선 무기 발견","contents":"1:34","link":"https://tv.naver.com/v/44450478","retrieved":1702790159646,"image":"https://phinf.pstatic.net/tvcast/20231217_78/HxIln_1702788222900AfcDk_JPEG/1702788036860.jpg?type=f194_109_blend"},{"title":"[리빙톡] \"3시간 넘는 출퇴근 시간…매일이 고돼 우울해요\"","contents":"2:47","link":"https://tv.naver.com/v/44389949","retrieved":1702775979788,"image":"https://phinf.pstatic.net/tvcast/20231215_44/iMzAI_17026280504381sny9_JPEG/1702628041468.jpg?type=f194_109_blend"},{"title":"이스라엘, 하마스 손아귀 벗어난 인질 3명 실수로 사살","contents":"1:31","link":"https://tv.naver.com/v/44425275","retrieved":1702714828633,"image":"https://phinf.pstatic.net/tvcast/20231216_250/9iBN6_1702711578160VutEP_JPEG/1702711459720.jpg?type=f194_109_blend"},{"title":"이정후, 샌프란시스코 입단식…\"한국에서 온 바람의 손자\"","contents":"1:51","link":"https://tv.naver.com/v/44419864","retrieved":1702703798262,"image":"https://phinf.pstatic.net/tvcast/20231216_81/Oxj81_1702701038646Jpxqx_JPEG/1702700907320.jpg?type=f194_109_blend"},{"title":"\"러시아 5발 쏠때 겨우 한발 쏴\"…우크라 포탄 부족에 패전 공포","contents":"2:43","link":"https://tv.naver.com/v/44390069","retrieved":1702628568095,"image":"https://phinf.pstatic.net/tvcast/20231215_51/5vUfh_1702628171054BmSw4_JPEG/1702627517218.jpg?type=f194_109_blend"},{"title":"조두순 야간 무단외출했다 40여분 만에 귀가…이유 묻자","contents":"1:53","link":"https://tv.naver.com/v/44389718","retrieved":1702628568095,"image":"https://phinf.pstatic.net/tvcast/20231215_182/QMgVb_17026278054611EcJt_JPEG/1702627187609.jpg?type=f194_109_blend"},{"title":"하마스가 쏜 로켓 '쾅'…질주하며 막아낸 이스라엘 전차의 비밀","contents":"1:50","link":"https://tv.naver.com/v/44389714","retrieved":1702628568096,"image":"https://phinf.pstatic.net/tvcast/20231215_269/hkk6b_17026278017042tqWs_JPEG/1702627787149.jpg?type=f194_109_blend"},{"title":"푸틴, 우크라 사태 후 첫 기자회견…젤렌스키 갑자기 독일행","contents":"3:30","link":"https://tv.naver.com/v/44384502","retrieved":1702624588015,"image":"https://phinf.pstatic.net/tvcast/20231215_85/MH2YJ_1702622541749kckEU_JPEG/1702622469697.jpg?type=f194_109_blend"},{"title":"베이징서 지하철 열차 분리 사고…승객 30여명 부상","contents":"1:13","link":"https://tv.naver.com/v/44384373","retrieved":1702624588016,"image":"https://phinf.pstatic.net/tvcast/20231215_272/CnpyZ_1702622396353TSvSy_JPEG/1702622033868.jpg?type=f194_109_blend"},{"title":"이스라엘군 '하마스 테러 공작원 투항' 영상 첫 공개","contents":"2:08","link":"https://tv.naver.com/v/44371571","retrieved":1702610334692,"image":"https://phinf.pstatic.net/tvcast/20231215_36/VxXHJ_1702609073819Pd6yD_JPEG/1702608693634.jpg?type=f194_109_blend"},{"title":"\"가자 아이들 피 흘려\"…튀르키예 스타벅스서 괴한 총기 난사","contents":"2:28","link":"https://tv.naver.com/v/44371484","retrieved":1702610334694,"image":"https://phinf.pstatic.net/tvcast/20231215_142/QXpPw_1702609076849oYlyI_JPEG/1702609075161.jpg?type=f194_109_blend"},{"title":"\"신와르 잡으면 5억 준다\"…이스라엘, 거액 현상금 내걸고 추적","contents":"2:04","link":"https://tv.naver.com/v/44369655","retrieved":1702607486132,"image":"https://phinf.pstatic.net/tvcast/20231215_92/JdGIq_17026071091536fTLe_JPEG/1702606923795.jpg?type=f194_109_blend"},{"title":"가수 박유천 4억·'쌍칼' 박준규 3억…고액 체납자 명단 공개","contents":"1:38","link":"https://tv.naver.com/v/44340609","retrieved":1702552536826,"image":"https://phinf.pstatic.net/tvcast/20231214_6/COm0L_1702549617474UmFiO_JPEG/1702549607073.jpg?type=f194_109_blend"},{"title":"쉴새없이 탕탕탕! 수류탄 펑!…보디캠에 담긴 이-하마스 교전","contents":"2:58","link":"https://tv.naver.com/v/44335127","retrieved":1702545477149,"image":"https://phinf.pstatic.net/tvcast/20231214_279/3J6NW_17025433168093HcFk_JPEG/1702543134495.jpg?type=f194_109_blend"},{"title":"'서울의 봄'의 힘…11월 한국영화 매출, 팬데믹 이전 70％ 회복","contents":"2:22","link":"https://tv.naver.com/v/44333885","retrieved":1702542142829,"image":"https://phinf.pstatic.net/tvcast/20231214_100/lTpB8_17025421205288MSuY_JPEG/1702541390566.jpg?type=f194_109_blend"},{"title":"\"하마스 배제는 망상\" \"승리할때까지 전쟁\"…전후 가자지구는?","contents":"2:42","link":"https://tv.naver.com/v/44332053","retrieved":1702542142830,"image":"https://phinf.pstatic.net/tvcast/20231214_260/W038O_1702540428384wqDA3_JPEG/1702540244532.jpg?type=f194_109_blend"},{"title":"미 코리아타운 '돼지곰탕', NYT '뉴욕 최고요리' 선정","contents":"1:34","link":"https://tv.naver.com/v/44331133","retrieved":1702542142832,"image":"https://phinf.pstatic.net/tvcast/20231214_134/gGqwH_170253960913287FSk_JPEG/1702539584360.jpg?type=f194_109_blend"},{"title":"머스크의 또 다른 야심작…테슬라 로봇 '옵티머스 2세대' 공개","contents":"2:36","link":"https://tv.naver.com/v/44329377","retrieved":1702538189277,"image":"https://phinf.pstatic.net/tvcast/20231214_8/5cwow_1702538063158bO1Wc_JPEG/1702537664314.jpg?type=f194_109_blend"},{"title":"\"알라의 분노 겪을 것\"…이스라엘 비난 연설 도중 심장마비 '쿵'","contents":"1:44","link":"https://tv.naver.com/v/44328727","retrieved":1702538189277,"image":"https://phinf.pstatic.net/tvcast/20231214_179/fWDd1_170253743240748sHQ_JPEG/1702537411646.jpg?type=f194_109_blend"},{"title":"지드래곤 마약 무혐의…경찰 \"제보 구체적, 부실 수사 아니었다\"","contents":"1:56","link":"https://tv.naver.com/v/44328492","retrieved":1702538189278,"image":"https://phinf.pstatic.net/tvcast/20231214_48/nmK7N_1702537197346Wi9Rk_JPEG/1702536666058.jpg?type=f194_109_blend"},{"title":"5살 때 스스로 배에 인슐린 주사…10년 후 소년의 꿈은","contents":"6:32","link":"https://tv.naver.com/v/44323054","retrieved":1702534983136,"image":"https://phinf.pstatic.net/tvcast/20231214_89/lJ9hQ_1702532249401jdowe_JPEG/1702532202423.jpg?type=f194_109_blend"},{"title":"이스라엘 '하마스 터널 침수작전' 개시…미국은 '인도주의 촉구'","contents":"2:40","link":"https://tv.naver.com/v/44320831","retrieved":1702531046330,"image":"https://phinf.pstatic.net/tvcast/20231214_63/RflMf_1702529987250zRm7i_JPEG/1702529962631.jpg?type=f194_109_blend"},{"title":"윤 대통령, 헤이그 리더잘·이준 기념관 방문…우리 정상 처음","contents":"2:36","link":"https://tv.naver.com/v/44315259","retrieved":1702523953304,"image":"https://phinf.pstatic.net/tvcast/20231214_212/om9Dx_17025231238445o95b_JPEG/1702522899325.jpg?type=f194_109_blend"},{"title":"폴란드 새 연립정부 출범…'K-방산 수출 타격' 우려","contents":"2:27","link":"https://tv.naver.com/v/44314216","retrieved":1702523953305,"image":"https://phinf.pstatic.net/tvcast/20231214_170/KEKEy_1702521775008F59dB_JPEG/1702521453635.jpg?type=f194_109_blend"},{"title":"\"지지 잃어\" \"계속 대립\"…바이든-네타냐후 전후구상 두고 설전","contents":"2:25","link":"https://tv.naver.com/v/44276118","retrieved":1702455755476,"image":"https://phinf.pstatic.net/tvcast/20231213_19/1xUlf_1702455644259hk3nM_JPEG/1702455564453.jpg?type=f194_109_blend"},{"title":"\"허락 없이 못 지나간다\"…예멘반군, 홍해 선박 항해 봉쇄","contents":"2:08","link":"https://tv.naver.com/v/44275401","retrieved":1702455755477,"image":"https://phinf.pstatic.net/tvcast/20231213_180/Cmg02_1702454993647jpRi3_JPEG/1702454980741.jpg?type=f194_109_blend"},{"title":"구단 회장이 심판 얼굴에 '강펀치'…FIFA 분노 \"축구 죽이는 암\"","contents":"1:50","link":"https://tv.naver.com/v/44275258","retrieved":1702455755481,"image":"https://phinf.pstatic.net/tvcast/20231213_40/ZjKnK_1702454850698ugO0e_JPEG/1702454391250.jpg?type=f194_109_blend"}]}