{"title":"연합뉴스 ─ 네이버TV","url":"https://tv.naver.com/yonhapnews/clips","favicon":"https://tv.naver.com/yonhapnews/favicon.ico","elements":[{"title":"통째로 뜯겨 강물에 '둥둥'…태풍 '므르복'에 알래스카 홍수","contents":"1:00","link":"https://tv.naver.com/v/29299275","retrieved":1663579725910,"image":"https://phinf.pstatic.net/tvcast/20220919_97/UwFxY_1663576911620q3fq4_JPEG/1663576909628.jpg?type=f194_109_blend"},{"title":"'백만송이 장미' 원곡 러 가수도 푸틴 비판…\"나도 스파이냐\"","contents":"1:22","link":"https://tv.naver.com/v/29299177","retrieved":1663579725911,"image":"https://phinf.pstatic.net/tvcast/20220919_265/4bbhK_1663576643823Iujl8_JPEG/1663575428066.jpg?type=f194_109_blend"},{"title":"북한 동영상 앱 시청 1위는…3D 애니메이션 '악마를 이긴 억쇠'","contents":"2:24","link":"https://tv.naver.com/v/29299066","retrieved":1663576493778,"image":"https://phinf.pstatic.net/tvcast/20220919_27/Vz4em_1663576365735jnI1v_JPEG/1663575568317.jpg?type=f194_109_blend"},{"title":"미 국방부, '중국산 부품' 전쟁 선포?…AI까지 동원해 색출","contents":"2:51","link":"https://tv.naver.com/v/29298891","retrieved":1663576493778,"image":"https://phinf.pstatic.net/tvcast/20220919_34/2piUS_1663575964720FIanp_JPEG/1663574659953.jpg?type=f194_109_blend"},{"title":"신당역 '스토킹 살해범'은 31세 전주환…\"공개 장소·계획 살인\"","contents":"1:21","link":"https://tv.naver.com/v/29298754","retrieved":1663576493779,"image":"https://phinf.pstatic.net/tvcast/20220919_173/ZzQyC_1663575647423EktDB_JPEG/1663575574347.jpg?type=f194_109_blend"},{"title":"'세기의 장례식' 영국 여왕 국장…역대급 조문외교에 '보안작전'","contents":"2:59","link":"https://tv.naver.com/v/29298381","retrieved":1663576493782,"image":"https://phinf.pstatic.net/tvcast/20220919_99/WK5Cd_16635748189284Yu0J_JPEG/1663574793126.jpg?type=f194_109_blend"},{"title":"\"러시아, 이란제 '자폭드론' 우크라 전장 투입\"","contents":"2:28","link":"https://tv.naver.com/v/29297394","retrieved":1663573398707,"image":"https://phinf.pstatic.net/tvcast/20220919_230/ffzoQ_16635724610814BYD2_JPEG/1663571738646.jpg?type=f194_109_blend"},{"title":"태풍 난마돌, 부산 근접…경남 강풍·호우 경보","contents":"2:39","link":"https://tv.naver.com/v/29292883","retrieved":1663563439373,"image":"https://phinf.pstatic.net/tvcast/20220919_292/S6oeM_16635625419231tpGl_JPEG/1663562524141.jpg?type=f194_109_blend"},{"title":"GPS 조작앱 깔고 정신과 방문 신당역 살해범,치밀한 범행 계획","contents":"2:03","link":"https://tv.naver.com/v/29290897","retrieved":1663563439377,"image":"https://phinf.pstatic.net/tvcast/20220919_174/hoXQX_1663556868170eMOiE_JPEG/1663556841537.jpg?type=f194_109_blend"},{"title":"대만서 6.8 강진으로 건물·다리 붕괴, 열차 탈선","contents":"1:56","link":"https://tv.naver.com/v/29290776","retrieved":1663563439378,"image":"https://phinf.pstatic.net/tvcast/20220919_53/Ap2wt_1663556571027b3A4K_JPEG/1663556198689.jpg?type=f194_109_blend"},{"title":"윤대통령 \"자유의 수호자 여왕 못 잊어\"…찰스 3세 \"깊은 감사\"","contents":"1:36","link":"https://tv.naver.com/v/29290400","retrieved":1663563439380,"image":"https://phinf.pstatic.net/tvcast/20220919_226/rEKkI_1663555622779uaNkI_JPEG/1663555511104.jpg?type=f194_109_blend"},{"title":"일본 강타한 태풍 '난마돌'…강풍·물폭탄에 830만명 피난 권고","contents":"3:07","link":"https://tv.naver.com/v/29290226","retrieved":1663563439386,"image":"https://phinf.pstatic.net/tvcast/20220919_212/MnmGm_16635552650738qtAX_JPEG/1663553889799.jpg?type=f194_109_blend"},{"title":"인도가 돌려달라는 다이아몬드, 커밀라 왕비 품으로?","contents":"3:58","link":"https://tv.naver.com/v/29287204","retrieved":1663554975074,"image":"https://phinf.pstatic.net/tvcast/20220919_260/GPM1f_1663544252279syoB4_JPEG/1663544155916.jpg?type=f194_109_blend"},{"title":"[톺뉴스] KOREA의 한글 이름이 조선이라고?","contents":"1:00","link":"https://tv.naver.com/v/29249762","retrieved":1663539911808,"image":"https://phinf.pstatic.net/tvcast/20220916_220/YVY0h_1663320182251LUhbe_JPEG/1663320036208.jpg?type=f194_109_blend"},{"title":"영국 여왕 참배에 16시간…슈퍼스타 베컴, 관앞에서 '눈물 글썽'","contents":"1:25","link":"https://tv.naver.com/v/29276809","retrieved":1663485786394,"image":"https://phinf.pstatic.net/tvcast/20220918_217/DpV3r_1663483232701m8Oge_JPEG/1663483219042.jpg?type=f194_109_blend"},{"title":"부은 얼굴에 가발, 쉰 목소리…\"안성기, 1년 넘게 혈액암 투병\"","contents":"1:31","link":"https://tv.naver.com/v/29274660","retrieved":1663476118392,"image":"https://phinf.pstatic.net/tvcast/20220918_247/YSQTV_1663471823295zsMlx_JPEG/1663471678367.jpg?type=f194_109_blend"},{"title":"[리빙톡] 무릎 통증 완화엔 '이 자세'?…오히려 악화할 수도","contents":"2:29","link":"https://tv.naver.com/v/29221910","retrieved":1663453438693,"image":"https://phinf.pstatic.net/tvcast/20220915_40/ce18O_1663231996348V32na_JPEG/1663231932050.jpg?type=f194_109_blend"},{"title":"[포켓이슈] \"누가 수동으로 운전해요\"…1종도 자동으로 딸 수 있을까?","contents":"2:19","link":"https://tv.naver.com/v/29245697","retrieved":1663367215454,"image":"https://phinf.pstatic.net/tvcast/20220916_233/xyMuE_1663312164584oJx18_JPEG/1663312144623.jpg?type=f194_109_blend"},{"title":"中 후난성 초고층 빌딩에서 대형 화재 발생…인명 피해 없어","contents":"1:22","link":"https://tv.naver.com/v/29254533","retrieved":1663336490642,"image":"https://phinf.pstatic.net/tvcast/20220916_152/SnVdL_1663333635413rBsUx_JPEG/1663333428466.jpg?type=f194_109_blend"},{"title":"신당역 역무원 스토킹 살해범 영장 심사 종료","contents":"1:30","link":"https://tv.naver.com/v/29250820","retrieved":1663324084325,"image":"https://phinf.pstatic.net/tvcast/20220916_220/jlQ9L_16633230869255dMHP_JPEG/1663323023662.jpg?type=f194_109_blend"},{"title":"발전소 '쾅' 댐 '쾅'…러, 기간시설 정밀 타격 전략으로 수정?","contents":"2:33","link":"https://tv.naver.com/v/29249495","retrieved":1663320454866,"image":"https://phinf.pstatic.net/tvcast/20220916_190/mcerI_16633195444134hoKw_JPEG/1663318734099.jpg?type=f194_109_blend"},{"title":"[영상] 캐나다 곤돌라 케이블 절단범 공개수배…현상금 무려 5억원!","contents":"2:13","link":"https://tv.naver.com/v/29249266","retrieved":1663320454867,"image":"https://phinf.pstatic.net/tvcast/20220916_242/v64TG_1663318955086rStLg_JPEG/1663318927311.jpg?type=f194_109_blend"},{"title":"피해자 원치않아도 처벌?…스토킹에 무력한 스토킹처벌법 손본다","contents":"3:01","link":"https://tv.naver.com/v/29248744","retrieved":1663320454875,"image":"https://phinf.pstatic.net/tvcast/20220916_116/Ao9PP_1663317887806OcTbu_JPEG/1663317402974.jpg?type=f194_109_blend"},{"title":"영국 여왕 관 지키던 백발 경비병, 의식 잃고 '쿵'","contents":"1:49","link":"https://tv.naver.com/v/29248135","retrieved":1663317057193,"image":"https://phinf.pstatic.net/tvcast/20220916_166/VPr6A_1663316727592ohVyR_JPEG/1663316360199.jpg?type=f194_109_blend"},{"title":"교황, 서방의 우크라 무기 지원에 \"도덕적으로 용납할 수 있어\"","contents":"2:28","link":"https://tv.naver.com/v/29248033","retrieved":1663317057198,"image":"https://phinf.pstatic.net/tvcast/20220916_17/IKhG8_166331652640338ffg_JPEG/1663316038206.jpg?type=f194_109_blend"},{"title":"800억대 영빈관 신축 논란…\"국격·국익 도움 vs 양치기 예산\"","contents":"1:47","link":"https://tv.naver.com/v/29247737","retrieved":1663317057201,"image":"https://phinf.pstatic.net/tvcast/20220916_258/YOvR0_1663315908870FeOVK_JPEG/1663315617749.jpg?type=f194_109_blend"},{"title":"유엔 北인권보고관 \"중국에 구금된 탈북민 2천 명\"","contents":"1:32","link":"https://tv.naver.com/v/29246258","retrieved":1663313579483,"image":"https://phinf.pstatic.net/tvcast/20220916_52/C3ph5_1663313197660LH2x1_JPEG/1663312739154.jpg?type=f194_109_blend"},{"title":"맥도날드 사장 \"시카고 범죄 급증해 영업 어려울 지경\"","contents":"2:22","link":"https://tv.naver.com/v/29245033","retrieved":1663313579485,"image":"https://phinf.pstatic.net/tvcast/20220916_178/ieNoi_1663310993374FbUuL_JPEG/1663310880771.jpg?type=f194_109_blend"},{"title":"'ATACMS' 콕 집은 경고?…러, 미에 \"장거리 미사일 제공말라\"","contents":"1:38","link":"https://tv.naver.com/v/29242546","retrieved":1663308624087,"image":"https://phinf.pstatic.net/tvcast/20220916_2/T5TLL_1663306669248GJWhH_JPEG/1663306407221.jpg?type=f194_109_blend"},{"title":"[영상] 마라도나도 제쳤다…'농구 황제' 조던 결승전 유니폼 141억 낙찰","contents":"2:29","link":"https://tv.naver.com/v/29242466","retrieved":1663308624088,"image":"https://phinf.pstatic.net/tvcast/20220916_108/CHHM3_16633065517883buzP_JPEG/1663306516556.jpg?type=f194_109_blend"}]}