{"title":"연합뉴스 ─ 네이버TV","url":"https://tv.naver.com/yonhapnews/clips","favicon":"https://tv.naver.com/yonhapnews/favicon.ico","elements":[{"title":"'대만 갈등' 미·중 일촉즉발…'제2의 쿠바 미사일 위기' 번질까","contents":"3:16","link":"https://tv.naver.com/v/28347389","retrieved":1659522366011,"image":"https://phinf.pstatic.net/tvcast/20220803_89/qdenj_1659520601732vW7VK_JPEG/1659520132125.jpg?type=f194_109_blend"},{"title":"북한판 블랙이글스?…평양 밤하늘에 '불꽃 뿜는' 전투기들","contents":"3:00","link":"https://tv.naver.com/v/28346742","retrieved":1659522366012,"image":"https://phinf.pstatic.net/tvcast/20220803_234/e4Qei_1659518553294CQlW9_JPEG/1659518551142.jpg?type=f194_109_blend"},{"title":"금감원·경찰에 전화했는데 사기범이?…피싱방지 앱도 가짜였다","contents":"3:31","link":"https://tv.naver.com/v/28346702","retrieved":1659518526866,"image":"https://phinf.pstatic.net/tvcast/20220803_154/t4jkj_1659518472346pJ9Yr_JPEG/1659518071772.jpg?type=f194_109_blend"},{"title":"동틀 무렵 집중된 경기지역 장대비…차량 잠기고 빗길 사고도","contents":"1:20","link":"https://tv.naver.com/v/28345660","retrieved":1659518526869,"image":"https://phinf.pstatic.net/tvcast/20220803_61/hzcOa_1659516339271HDX6t_JPEG/1659516153393.jpg?type=f194_109_blend"},{"title":"브라질 샴쌍둥이, 기적적으로 분리수술 성공…VR로 수개월 준비","contents":"1:42","link":"https://tv.naver.com/v/28345587","retrieved":1659518526871,"image":"https://phinf.pstatic.net/tvcast/20220803_36/XO2lD_1659516194204rd22D_JPEG/1659515705381.jpg?type=f194_109_blend"},{"title":"대만 총통 만난 펠로시 \"中, 美의원 대만 방문 못막아\"","contents":"1:56","link":"https://tv.naver.com/v/28345205","retrieved":1659518526872,"image":"https://phinf.pstatic.net/tvcast/20220803_45/kjtTy_1659515563984ugRSk_JPEG/1659515547098.jpg?type=f194_109_blend"},{"title":"또 평상이랑 테이블이…경기도 하천·계곡 무단점용 '수두룩'","contents":"2:41","link":"https://tv.naver.com/v/28343605","retrieved":1659515430186,"image":"https://phinf.pstatic.net/tvcast/20220803_275/JCSPn_1659512761949KIJmu_JPEG/1659511817378.jpg?type=f194_109_blend"},{"title":"\"위로받으려는 거 아니에요\"…학부모 대표는 장관 손을 뿌리쳤다","contents":"2:19","link":"https://tv.naver.com/v/28343211","retrieved":1659515430188,"image":"https://phinf.pstatic.net/tvcast/20220803_262/SHCNW_1659511747230NsSkb_JPEG/1659511716796.jpg?type=f194_109_blend"},{"title":"美, '푸틴 연인' 카바예바 제재…러 의원·군인 893명 비자 동결","contents":"1:47","link":"https://tv.naver.com/v/28339790","retrieved":1659505372245,"image":"https://phinf.pstatic.net/tvcast/20220803_174/T6sWm_1659503260559js97c_JPEG/1659502323219.jpg?type=f194_109_blend"},{"title":"中, 펠로시 방문에 '대만 포위' 무력 시위…美대사도 심야 초치","contents":"2:59","link":"https://tv.naver.com/v/28337019","retrieved":1659500287707,"image":"https://phinf.pstatic.net/tvcast/20220803_72/vmmc9_1659495640533POzlD_JPEG/1659495145436.jpg?type=f194_109_blend"},{"title":"美中 항모 배치·전투기 출격…펠로시 대만 방문 '초긴장 7시간'","contents":"1:40","link":"https://tv.naver.com/v/28336828","retrieved":1659500287710,"image":"https://phinf.pstatic.net/tvcast/20220803_234/5Lrmo_1659495116283rbgnp_JPEG/1659494926110.jpg?type=f194_109_blend"},{"title":"우크라 남부 헤르손에 병력 총출동…전쟁 승패 좌우할 듯","contents":"1:20","link":"https://tv.naver.com/v/28336766","retrieved":1659500287712,"image":"https://phinf.pstatic.net/tvcast/20220803_216/qIdWV_1659494936994rlYrj_JPEG/1659494935112.jpg?type=f194_109_blend"},{"title":"도살 위기 23마리 유기견 구했지만…입양 안되면 안락사 불가피","contents":"1:56","link":"https://tv.naver.com/v/28336372","retrieved":1659500287713,"image":"https://phinf.pstatic.net/tvcast/20220803_198/kKHUp_16594937357657K6Pf_JPEG/1659493686286.jpg?type=f194_109_blend"},{"title":"누가 뚫었지?…칠레에 직경 25m·깊이 200m 초대형 싱크홀","contents":"1:45","link":"https://tv.naver.com/v/28336193","retrieved":1659500287715,"image":"https://phinf.pstatic.net/tvcast/20220803_168/9jhtV_1659493228465M7Cxt_JPEG/1659493005125.jpg?type=f194_109_blend"},{"title":"[Why요?] 비스킷에 구멍은 왜 있는 걸까?","contents":"0:57","link":"https://tv.naver.com/v/28322949","retrieved":1659479055433,"image":"https://phinf.pstatic.net/tvcast/20220802_264/tpP4f_16594311268048OAn2_JPEG/1659431055333.jpg?type=f194_109_blend"},{"title":"박순애 \"국민 원치 않으면 정책 폐기 가능\"","contents":"1:26","link":"https://tv.naver.com/v/28326492","retrieved":1659444482546,"image":"https://phinf.pstatic.net/tvcast/20220802_57/Dajte_16594429674222722N_JPEG/1659442646118.jpg?type=f194_109_blend"},{"title":"[스타트업발언대] 동물단백질·설탕 대체식품 개발 '올인' 한녹엽 인테이크 대표","contents":"6:41","link":"https://tv.naver.com/v/28323296","retrieved":1659479055436,"image":"https://phinf.pstatic.net/tvcast/20220802_235/GQ8C7_1659432265121aQCvf_JPEG/1659432208991.jpg?type=f194_109_blend"},{"title":"펠로시 방문 긴장 최고조…\"中군용기 대만해협 중간선 근접비행\"","contents":"2:37","link":"https://tv.naver.com/v/28322942","retrieved":1659432114401,"image":"https://phinf.pstatic.net/tvcast/20220802_203/83hBq_1659431112917vBdLF_JPEG/1659430030477.jpg?type=f194_109_blend"},{"title":"바이든 \"정의 실현\"…'9·11 배후' 알자와히리 21년 만에 제거","contents":"2:30","link":"https://tv.naver.com/v/28322610","retrieved":1659432114403,"image":"https://phinf.pstatic.net/tvcast/20220802_213/Gp28D_1659430162018gJFw6_JPEG/1659429563220.jpg?type=f194_109_blend"},{"title":"지구온난화로 바다거북 대가 끊겨?…플로리다 4년간 수컷 씨말라","contents":"1:19","link":"https://tv.naver.com/v/28321838","retrieved":1659428983104,"image":"https://phinf.pstatic.net/tvcast/20220802_93/9QFbz_1659428287369IKzNr_JPEG/1659427611178.jpg?type=f194_109_blend"},{"title":"'기러기·토마토'…넷플릭스도 머리 싸맨 '우영우' 영어 자막","contents":"3:12","link":"https://tv.naver.com/v/28321186","retrieved":1659475315919,"image":"https://phinf.pstatic.net/tvcast/20220803_94/mnglb_1659484361337vetkF_JPEG/1659484359040.jpg?type=f194_109_blend"},{"title":"전·현직 대통령, 제주도와 서울 사저에서 각각 '휴가 모드'","contents":"1:50","link":"https://tv.naver.com/v/28320858","retrieved":1659428983105,"image":"https://phinf.pstatic.net/tvcast/20220802_13/3mUoX_1659426026647fspfz_JPEG/1659425399818.jpg?type=f194_109_blend"},{"title":"'외계인 흔적일까'…호주 농장에 떨어진 검게 탄 괴물체 정체는","contents":"2:31","link":"https://tv.naver.com/v/28320374","retrieved":1659424980589,"image":"https://phinf.pstatic.net/tvcast/20220802_189/0o2df_1659424841142Mu4i5_JPEG/1659424762512.jpg?type=f194_109_blend"},{"title":"\"평양은 7차 핵실험 준비\"…NPT 회의서 북핵 우려 잇따라","contents":"3:19","link":"https://tv.naver.com/v/28317752","retrieved":1659419195133,"image":"https://phinf.pstatic.net/tvcast/20220802_281/PKDoN_1659418317085dLjdU_JPEG/1659417866709.jpg?type=f194_109_blend"},{"title":"\"펠로시, 오늘 밤 대만 도착\"…중국 \"손 놓고 있지 않을 것\"","contents":"2:31","link":"https://tv.naver.com/v/28315022","retrieved":1659414952071,"image":"https://phinf.pstatic.net/tvcast/20220802_266/tAFno_1659410128159AY9Hp_JPEG/1659410109175.jpg?type=f194_109_blend"},{"title":"'만 5세 입학' 반대 확산…교육부, 뒤늦게 \"사회적 합의 도출\"","contents":"3:30","link":"https://tv.naver.com/v/28314607","retrieved":1659414952072,"image":"https://phinf.pstatic.net/tvcast/20220802_114/8Vfjo_1659408866269auHzQ_JPEG/1659408832939.jpg?type=f194_109_blend"},{"title":"국방장관 \"BTS 입대해도 해외공연 가능…인기에 도움 될 수도\"","contents":"1:29","link":"https://tv.naver.com/v/28314477","retrieved":1659414952074,"image":"https://phinf.pstatic.net/tvcast/20220802_140/INBsd_1659408566214tdg2n_JPEG/1659408002623.jpg?type=f194_109_blend"},{"title":"다누리, 누리호 아닌 스페이스X 팰컨 타고 달에 가는 이유","contents":"10:36","link":"https://tv.naver.com/v/28311596","retrieved":1659407124779,"image":"https://phinf.pstatic.net/tvcast/20220802_208/DpTtd_1659396738101kTdmP_JPEG/1659396661587.jpg?type=f194_109_blend"},{"title":"[Why요?] 매미는 자기 소리가 안 시끄러울까?","contents":"0:57","link":"https://tv.naver.com/v/28290430","retrieved":1659392658734,"image":"https://phinf.pstatic.net/tvcast/20220801_66/qTA4n_1659319528369lE0hd_JPEG/1659319474122.jpg?type=f194_109_blend"},{"title":"\"어린이 충격\" vs \"어차피 생선\"…이마트 '상어 포토존' 논란","contents":"1:53","link":"https://tv.naver.com/v/28302927","retrieved":1659357968581,"image":"https://phinf.pstatic.net/tvcast/20220801_70/DF2Bt_1659353711861dl8gu_JPEG/1659353595180.jpg?type=f194_109_blend"}]}