{"title":"연합뉴스 ─ 네이버TV","url":"https://tv.naver.com/yonhapnews/clips","favicon":"https://tv.naver.com/yonhapnews/favicon.ico","elements":[{"title":"우크라 \"푸틴 권력 무너지고 있어\"…러 \"적 무기 2천500개 파괴\"","contents":"2:57","link":"https://tv.naver.com/v/37657018","retrieved":1688447990244,"image":"https://phinf.pstatic.net/tvcast/20230704_123/bMkCg_1688447200552bpyr9_JPEG/1688447187669.jpg?type=f194_109_blend"},{"title":"러 \"우크라, 크림반도 수장 암살 시도…30대 용의자 체포\"","contents":"1:51","link":"https://tv.naver.com/v/37656169","retrieved":1688447990248,"image":"https://phinf.pstatic.net/tvcast/20230704_285/ZI9nP_1688445909208GnaNC_JPEG/1688445125016.jpg?type=f194_109_blend"},{"title":"나토,'유럽 방위' 새판 짠다…30만군 대비 태세","contents":"2:19","link":"https://tv.naver.com/v/37651852","retrieved":1688439762673,"image":"https://phinf.pstatic.net/tvcast/20230704_7/NlFgO_16884387934394D6kF_JPEG/1688438590566.jpg?type=f194_109_blend"},{"title":"10대 총격 사망 일주일, 프랑스 폭력시위 소강국면 접어드나","contents":"2:53","link":"https://tv.naver.com/v/37651705","retrieved":1688439762673,"image":"https://phinf.pstatic.net/tvcast/20230704_167/RrD22_1688438570380tk1rb_JPEG/1688438549501.jpg?type=f194_109_blend"},{"title":"중국 함대 서아프리카 잇단 친선방문…\"영향력 확대\"","contents":"1:45","link":"https://tv.naver.com/v/37651597","retrieved":1688439762674,"image":"https://phinf.pstatic.net/tvcast/20230704_39/jGZNc_1688438401533wds8y_JPEG/1688438375969.jpg?type=f194_109_blend"},{"title":"팔레스타인 난민촌 불도저로 밀고 드론으로 폭격한 이스라엘","contents":"2:08","link":"https://tv.naver.com/v/37651151","retrieved":1688439762674,"image":"https://phinf.pstatic.net/tvcast/20230704_248/oKHBv_1688437675533PUQ6w_JPEG/1688437552972.jpg?type=f194_109_blend"},{"title":"전쟁중 우크라가 보낸 소녀 합창단…강릉 이재민들에게 희망","contents":"2:23","link":"https://tv.naver.com/v/37631190","retrieved":1688388099081,"image":"https://phinf.pstatic.net/tvcast/20230703_202/gu293_1688385979117Lc896_JPEG/1688385949410.jpg?type=f194_109_blend"},{"title":"\"프리고진 암살명령 내렸다\"…몰수한 재산은 '푸틴 연인' 차지?","contents":"2:23","link":"https://tv.naver.com/v/37625090","retrieved":1688379686336,"image":"https://phinf.pstatic.net/tvcast/20230703_50/3cpYM_1688376079998PO8VK_JPEG/1688376059530.jpg?type=f194_109_blend"},{"title":"시장 집까지 공격한 시위대…프랑스, 대테러부대 '지젠' 투입","contents":"1:47","link":"https://tv.naver.com/v/37624657","retrieved":1688376039574,"image":"https://phinf.pstatic.net/tvcast/20230703_118/LipJd_1688375359944Hq1Fr_JPEG/1688375344585.jpg?type=f194_109_blend"},{"title":"\"24시간 동안 전투 28번\"…동남부 전선 러-우크라 전투 격화","contents":"2:34","link":"https://tv.naver.com/v/37623860","retrieved":1688376039576,"image":"https://phinf.pstatic.net/tvcast/20230703_77/gb980_1688374230308LN51d_JPEG/1688373994058.jpg?type=f194_109_blend"},{"title":"'러브버그' 북한산 정상 백운대 뒤덮었지만 화학방역은 안 해","contents":"2:24","link":"https://tv.naver.com/v/37620578","retrieved":1688372702063,"image":"https://phinf.pstatic.net/tvcast/20230703_180/eQplS_1688369870164vQuKR_JPEG/1688369854941.jpg?type=f194_109_blend"},{"title":"'비행 전기차' 시험비행 첫 승인…출퇴근 혁명 다가오나","contents":"1:57","link":"https://tv.naver.com/v/37620373","retrieved":1688372702069,"image":"https://phinf.pstatic.net/tvcast/20230703_190/UDPPB_16883695872934h3Nz_JPEG/1688367808888.jpg?type=f194_109_blend"},{"title":"[풀영상] 영화 '바비' 내한 기자간담회｜마고 로비·아메리카 페레라·그레타 거윅 감독｜Ba","contents":"50:03","link":"https://tv.naver.com/v/37615236","retrieved":1688365544738,"image":"https://phinf.pstatic.net/tvcast/20230703_7/yQn6S_168836279071667tTC_JPEG/1688362464526.jpg?type=f194_109_blend"},{"title":"또 '만리장성' 꺾었다…신유빈-전지희, WTT 자그레브 복식 우승","contents":"2:37","link":"https://tv.naver.com/v/37614047","retrieved":1688361584266,"image":"https://phinf.pstatic.net/tvcast/20230703_287/gNId4_1688361234558PpbjJ_JPEG/1688360408128.jpg?type=f194_109_blend"},{"title":"'대반격' 우크라 바흐무트 공세에…러 최정예 부대 '착착' 집결","contents":"2:03","link":"https://tv.naver.com/v/37612893","retrieved":1688361584268,"image":"https://phinf.pstatic.net/tvcast/20230703_246/X0BoO_1688359566761UC66k_JPEG/1688359001038.jpg?type=f194_109_blend"},{"title":"'이란 막겠다' 이스라엘, 스텔스 전투기 F-35 추가 구매 승인","contents":"1:42","link":"https://tv.naver.com/v/37609488","retrieved":1688355088705,"image":"https://phinf.pstatic.net/tvcast/20230703_245/wEz0D_1688353536472cal1b_JPEG/1688353477528.jpg?type=f194_109_blend"},{"title":"유럽 지키랴 북한 막으랴…과로 시달리는 미 육군 방공부대","contents":"2:22","link":"https://tv.naver.com/v/37609259","retrieved":1688353237493,"image":"https://phinf.pstatic.net/tvcast/20230703_96/WnUkg_1688353057689BzRff_JPEG/1688353014267.jpg?type=f194_109_blend"},{"title":"프랑스 경전차, 우크라전 무용지물 전락…\"방호력 취약\"","contents":"2:11","link":"https://tv.naver.com/v/37609077","retrieved":1688353237497,"image":"https://phinf.pstatic.net/tvcast/20230703_246/V1gjP_1688352820643IwhEh_JPEG/1688352807355.jpg?type=f194_109_blend"},{"title":"독일서 빛난 스테이씨 \"해외 팬들과 음악 하나로 연결\"","contents":"2:49","link":"https://tv.naver.com/v/37590003","retrieved":1688289449834,"image":"https://phinf.pstatic.net/tvcast/20230702_92/Vlqs1_1688287067805oPpPP_JPEG/1688286511862.jpg?type=f194_109_blend"},{"title":"하이마스 아쉬움 달랜 '스톰 섀도' 우크라서 맹활약","contents":"2:34","link":"https://tv.naver.com/v/37586224","retrieved":1688278999472,"image":"https://phinf.pstatic.net/tvcast/20230702_248/xcU9c_1688276758327OhGva_JPEG/1688276061467.jpg?type=f194_109_blend"},{"title":"[리빙톡] 글루텐은 나쁘다?…'글루텐 프리'의 오해와 진실","contents":"2:26","link":"https://tv.naver.com/v/37544712","retrieved":1688253530230,"image":"https://phinf.pstatic.net/tvcast/20230630_19/0qdwk_1688115283521OYkSY_JPEG/1688115230156.jpg?type=f194_109_blend"},{"title":"코끼리 학대 논란에…스리랑카 생활 22년만에 태국으로 돌아가","contents":"2:09","link":"https://tv.naver.com/v/37566737","retrieved":1688195846510,"image":"https://phinf.pstatic.net/tvcast/20230701_153/DAyqM_1688194967956ss977_JPEG/1688194809784.jpg?type=f194_109_blend"},{"title":"새로 터 잡은 바그너 용병?…벨라루스 군기지 텐트 300여개 포착","contents":"1:53","link":"https://tv.naver.com/v/37562617","retrieved":1688185388889,"image":"https://phinf.pstatic.net/tvcast/20230701_173/zrPg8_16881831269225KazB_JPEG/1688182790777.jpg?type=f194_109_blend"},{"title":"또다른 '게임체인저' 에이태큼스…\"미, 우크라 지원 승인 대기\"","contents":"1:56","link":"https://tv.naver.com/v/37545943","retrieved":1688120451645,"image":"https://phinf.pstatic.net/tvcast/20230630_133/VbINQ_1688117593622r6RUO_JPEG/1688117579116.jpg?type=f194_109_blend"},{"title":"버진 갤럭틱, 첫 상업 우주비행 성공 \"800장 티켓 벌써 팔려\"","contents":"3:14","link":"https://tv.naver.com/v/37545170","retrieved":1688116756921,"image":"https://phinf.pstatic.net/tvcast/20230630_56/6mYEX_1688116133716DQg08_JPEG/1688115746005.jpg?type=f194_109_blend"},{"title":"축구판 '쩐의 전쟁'…일당 8억원이 아깝지 않은 이유","contents":"4:29","link":"https://tv.naver.com/v/37543820","retrieved":1688246176890,"image":"https://phinf.pstatic.net/tvcast/20230630_204/T7aaq_1688113854995C211M_JPEG/1688113765010.jpg?type=f194_109_blend"},{"title":"\"'반란 가담설' 러군 2인자, 바그너그룹 VIP 회원\"","contents":"2:27","link":"https://tv.naver.com/v/37543307","retrieved":1688113394956,"image":"https://phinf.pstatic.net/tvcast/20230630_180/Q2ZvR_1688113832738lgJc3_JPEG/1688113831151.jpg?type=f194_109_blend"},{"title":"하얏트호텔서 문신활보·난동 '수노아파'…3년 만에 사실상 와해","contents":"1:38","link":"https://tv.naver.com/v/37542152","retrieved":1688113394958,"image":"https://phinf.pstatic.net/tvcast/20230630_276/Vrj5Q_1688111580251JEqXi_JPEG/1688111078073.jpg?type=f194_109_blend"},{"title":"\"아내는 꺼냈는데 아이는\"…339㎜ 물폭탄에 돌 갓 지난 딸 잃어","contents":"2:46","link":"https://tv.naver.com/v/37541860","retrieved":1688113394959,"image":"https://phinf.pstatic.net/tvcast/20230630_94/KWveX_1688111229775Avnbi_JPEG/1688111185786.jpg?type=f194_109_blend"},{"title":"10대 총격 사망 항의시위 프랑스 불바다…경찰관 살인혐의 수사","contents":"3:01","link":"https://tv.naver.com/v/37539089","retrieved":1688109476412,"image":"https://phinf.pstatic.net/tvcast/20230630_289/RynmQ_1688107606643eI1t0_JPEG/1688106574514.jpg?type=f194_109_blend"}]}